magicmapper/__init__.py
magicmapper/magicmapper.py
magicmapper/tests/__init__.py
magicmapper/tests/test_magic.py
magicmapper-0.9.1.dist-info/LICENSE
magicmapper-0.9.1.dist-info/METADATA
magicmapper-0.9.1.dist-info/WHEEL
magicmapper-0.9.1.dist-info/top_level.txt
magicmapper-0.9.1.dist-info/RECORD
