Metadata-Version: 2.1
Name: magicmapper
Version: 0.9.1
Summary: Mapping data structures
Author-email: Matti Eiden <snaipperi@gmail.com>
License: MIT
Keywords: data,mapping
Classifier: Programming Language :: Python :: 3
Classifier: Development Status :: 5 - Production/Stable
Classifier: License :: OSI Approved :: MIT License
Classifier: Operating System :: OS Independent
Requires-Python: >=3.7
License-File: LICENSE
